trellotasks/__init__.py
trellotasks/__main__.py
trellotasks-0.2.0.dist-info/entry_points.txt
trellotasks-0.2.0.dist-info/WHEEL
trellotasks-0.2.0.dist-info/METADATA
trellotasks-0.2.0.dist-info/RECORD
